JsOperation.py
beierTools-0.0.7.dist-info/METADATA
beierTools-0.0.7.dist-info/WHEEL
beierTools-0.0.7.dist-info/top_level.txt
beierTools-0.0.7.dist-info/RECORD
