Metadata-Version: 2.1
Name: beierTools
Version: 0.0.7
Summary: Beier developments tools
Home-page: https://github.com/srx-2000/beier_tools
Author: Beier
Author-email: 1601684622@qq.com
License: MIT License
